roulette/__init__.py
roulette/logger.py
roulette/builder/__init__.py
roulette/builder/base_model.py
roulette/builder/builder.py
roulette/builder/constants.py
roulette/builder/data_prep.py
roulette/builder/save_load_model.py
roulette/builder/utils.py
roulette/evaluation/__init__.py
roulette/evaluation/constants.py
roulette/evaluation/experiment.py
roulette/evaluation/metrics.py
roulette/evaluation/monte_carlo.py
roulette/evaluation/norms.py
roulette/evaluation/simulation_data.py
roulette/evaluation/utils.py
roulette/evaluation/plotting/__init__.py
roulette/evaluation/plotting/hist.py
roulette/evaluation/plotting/result_data.py
roulette_ml-0.1.1.dist-info/LICENSE
roulette_ml-0.1.1.dist-info/METADATA
roulette_ml-0.1.1.dist-info/WHEEL
roulette_ml-0.1.1.dist-info/top_level.txt
roulette_ml-0.1.1.dist-info/RECORD
